mle_scheduler/__init__.py
mle_scheduler/_version.py
mle_scheduler/job.py
mle_scheduler/job_queue.py
mle_scheduler/cloud/__init__.py
mle_scheduler/cloud/gcp/__init__.py
mle_scheduler/cloud/gcp/file_manage_gcp.py
mle_scheduler/cloud/gcp/helpers_launch_gcp.py
mle_scheduler/cloud/gcp/job_manage_gcp.py
mle_scheduler/cloud/gcp/startup_script_gcp.py
mle_scheduler/cluster/__init__.py
mle_scheduler/cluster/sge/__init__.py
mle_scheduler/cluster/sge/helpers_launch_sge.py
mle_scheduler/cluster/sge/manage_sge.py
mle_scheduler/cluster/sge/startup_script_sge.py
mle_scheduler/cluster/slurm/__init__.py
mle_scheduler/cluster/slurm/helpers_launch_slurm.py
mle_scheduler/cluster/slurm/manage_slurm.py
mle_scheduler/cluster/slurm/startup_script_slurm.py
mle_scheduler/local/__init__.py
mle_scheduler/local/manage_local.py
mle_scheduler/ssh/__init__.py
mle_scheduler/ssh/file_manage_ssh.py
mle_scheduler/ssh/helpers_launch_ssh.py
mle_scheduler/ssh/job_manage_ssh.py
mle_scheduler/ssh/ssh_manager.py
mle_scheduler-0.0.8.dist-info/LICENSE
mle_scheduler-0.0.8.dist-info/METADATA
mle_scheduler-0.0.8.dist-info/WHEEL
mle_scheduler-0.0.8.dist-info/top_level.txt
mle_scheduler-0.0.8.dist-info/RECORD
