Metadata-Version: 2.1
Name: mle_scheduler
Version: 0.0.8
Summary: Machine Learning Experiment Job Scheduler
Home-page: https://github.com/mle-infrastructure/mle-scheduler
Download-URL: https://github.com/mle-infrastructure/mle-scheduler/archive/v0.0.8.tar.gz
Author: Robert Tjarko Lange
Author-email: robertlange0@gmail.com
Platform: any
Classifier: Programming Language :: Python :: 3.6
Classifier: Programming Language :: Python :: 3.7
Classifier: Programming Language :: Python :: 3.8
Classifier: Programming Language :: Python :: 3.9
Classifier: License :: OSI Approved :: MIT License
Classifier: Operating System :: OS Independent
Classifier: Topic :: Scientific/Engineering :: Artificial Intelligence
Requires-Python: >=3.6
License-File: LICENSE
Requires-Dist: numpy
Requires-Dist: dotmap
Requires-Dist: rich
Provides-Extra: examples
Requires-Dist: google-cloud-storage; extra == "examples"
Requires-Dist: paramiko; extra == "examples"
Requires-Dist: sshtunnel; extra == "examples"
Requires-Dist: scp; extra == "examples"
Requires-Dist: mle-logging; extra == "examples"
Requires-Dist: mle-hyperopt; extra == "examples"
Provides-Extra: full
Requires-Dist: google-cloud-storage; extra == "full"
Requires-Dist: paramiko; extra == "full"
Requires-Dist: sshtunnel; extra == "full"
Requires-Dist: scp; extra == "full"
